stubs/compton.toml
stubs/git.toml
stubs/i3status.toml
stubs/i3wm.toml
stubs/neovim.toml
stubs/proxychains.toml
stubs/ranger.toml
stubs/vim.toml
stubs/zsh.toml
tweedle/__init__.py
tweedle/cmd/__init__.py
tweedle/cmd/blog.py
tweedle/cmd/config.py
tweedle/cmd/manage.py
tweedle/cmd/plugin.py
tweedle/cmd/project.py
tweedle/cmd/spawn.py
tweedle/core.py
tweedle/entry.py
tweedle/util/__init__.py
tweedle/util/archive.py
tweedle/util/clickx.py
tweedle/util/cliview.py
tweedle/util/common.py
tweedle/util/fs.py
tweedle/util/log.py
tweedle/util/sh.py
tweedle-0.0.2.dist-info/entry_points.txt
tweedle-0.0.2.dist-info/LICENSE
tweedle-0.0.2.dist-info/WHEEL
tweedle-0.0.2.dist-info/METADATA
tweedle-0.0.2.dist-info/RECORD
